
<Section id="19" width="20" height="10" color="#e07777" filter="none">
	<Layer id="droids">
		<i id="123" patrol="[[5,3], [9,3]]"/>
	</Layer>
	<Layer id="lights">
		<i x="160" y="160"/>
		<i x="300" y="160"/>
	</Layer>
	<Layer id="los">
		<walls>
			<i d="1" x="42" y="42" w="268"/>
			<i d="2" x="308" y="42" h="66"/>
			<i d="1" x="308" y="106" w="258"/>
			<i d="2" x="564" y="106" h="76"/>
			<i d="3" x="308" y="180" w="258"/>
			<i d="2" x="308" y="180" h="66"/>
			<i d="3" x="42" y="244" w="268"/>
			<i d="0" x="42" y="42" h="204"/>
		</walls>
		<walls>
			<i d="1" x="50" y="66" w="60"/>
			<i d="2" x="108" y="66" h="44"/>
			<i d="3" x="50" y="108" w="60"/>
			<i d="0" x="50" y="66" h="44"/>
		</walls>
		<walls>
			<i d="1" x="50" y="112" w="30"/>
			<i d="2" x="78" y="112" h="64"/>
			<i d="3" x="50" y="174" w="30"/>
			<i d="0" x="50" y="112" h="64"/>
		</walls>
	</Layer>
	<Layer id="action">
		<i x="2" y="4" w="1" h="2" action="console"/>
		<i x="16" y="4" w="2" h="2" action="exit" lift="4"/>
	</Layer>
	<Layer id="collision">
		<i id="c4" x="80" y="87" w="60" h="44"/>
		<i id="c4" x="64" y="145" w="28" h="64"/>
		<i id="c1" x="174" y="31" w="280" h="20"/>
		<i id="c1" x="32" y="143" w="20" h="212"/>
		<i id="c1" x="176" y="255" w="276" h="20"/>
		<i id="c1" x="576" y="141" w="20" h="88"/>
		<i id="c4" x="336" y="69" w="52" h="72"/>
		<i id="c4" x="336" y="219" w="52" h="76"/>
		<i id="c1" x="464" y="95" w="212" h="20"/>
		<i id="c1" x="464" y="191" w="212" h="20"/>
	</Layer>
	<Layer id="background">
		<i id="m0e"/><i id="m09"/><i id="m08"/><i id="m09"/><i id="m08"/><i id="m09"/><i id="m08"/><i id="m09"/><i id="m08"/><i id="m09"/><i id="m08"/><i id="m0d"/><i /><i /><i /><i /><i /><i /><i /><i /><i id="m1a"/><i id="m39"/><i id="m34"/><i id="m35"/><i id="m34"/><i id="m35"/><i id="m34"/><i id="m35"/><i id="m34"/><i id="m35"/><i id="m38"/><i id="m1d"/><i /><i /><i /><i /><i /><i /><i /><i /><i id="m0a"/><i id="m27"/><i id="m4c"/><i id="m4d"/><i id="m4a"/><i id="m4b"/><i id="m4a"/><i id="m4b"/><i id="m4a"/><i id="m4b"/><i id="m2a"/><i id="m2b"/><i id="m08"/><i id="m09"/><i id="m08"/><i id="m09"/><i id="m08"/><i id="m09"/><i id="m08"/><i id="m0d"/><i id="m1a"/><i id="m37"/><i id="m5c"/><i id="m5d"/><i id="m5a"/><i id="m5b"/><i id="m5a"/><i id="m5b"/><i id="m5a"/><i id="m5b"/><i id="m3e"/><i id="m35"/><i id="m34"/><i id="m35"/><i id="m34"/><i id="m35"/><i id="m34"/><i id="m35"/><i id="m38"/><i id="m1b"/><i id="m0a"/><i id="m27"/><i id="m44"/><i id="m43"/><i id="m4a"/><i id="m4b"/><i id="m4a"/><i id="m4b"/><i id="m4a"/><i id="m4b"/><i id="m4a"/><i id="m4b"/><i id="m4a"/><i id="m4b"/><i id="m4a"/><i id="m4b"/><i id="m06"/><i id="m07"/><i id="m2a"/><i id="m0b"/><i id="m1a"/><i id="m37"/><i id="m54"/><i id="m51"/><i id="m5a"/><i id="m5b"/><i id="m5a"/><i id="m5b"/><i id="m5a"/><i id="m5b"/><i id="m5a"/><i id="m5b"/><i id="m5a"/><i id="m5b"/><i id="m5a"/><i id="m5b"/><i id="m16"/><i id="m17"/><i id="m3a"/><i id="m1b"/><i id="m0a"/><i id="m27"/><i id="m4a"/><i id="m4b"/><i id="m4a"/><i id="m4b"/><i id="m4a"/><i id="m4b"/><i id="m4a"/><i id="m4b"/><i id="m2e"/><i id="m29"/><i id="m28"/><i id="m29"/><i id="m28"/><i id="m29"/><i id="m28"/><i id="m29"/><i id="m24"/><i id="m0b"/><i id="m1a"/><i id="m37"/><i id="m5a"/><i id="m5b"/><i id="m5a"/><i id="m5b"/><i id="m5a"/><i id="m5b"/><i id="m5a"/><i id="m5b"/><i id="m3a"/><i id="m3b"/><i id="m18"/><i id="m19"/><i id="m18"/><i id="m19"/><i id="m18"/><i id="m19"/><i id="m18"/><i id="m33"/><i id="m0a"/><i id="m2b"/><i id="m28"/><i id="m29"/><i id="m28"/><i id="m29"/><i id="m28"/><i id="m29"/><i id="m28"/><i id="m29"/><i id="m26"/><i id="m23"/><i /><i /><i /><i /><i /><i /><i /><i /><i id="m30"/><i id="m19"/><i id="m18"/><i id="m19"/><i id="m18"/><i id="m19"/><i id="m18"/><i id="m19"/><i id="m18"/><i id="m19"/><i id="m18"/><i id="m33"/><i /><i /><i /><i /><i /><i /><i /><i />
	</Layer>
</Section>
